Workbook

Sheet Dashboard
B2: Nykaa (FSN E-Commerce Ventures) — FP&A Dashboard
B3: FY24 – FY27 | Data: screener.in | Prepared as an independent FP&A analysis exercise
B5: Select Fiscal Year: | D5: FY26
B7: Avg. Quarterly Revenue (₹ Cr) | D7: Avg. EBITDA Margin | F7: Total Revenue (₹ Cr)
B8: =AVERAGEIF(Actuals!C6:C18,$D$5,Actuals!D6:D18) -> 2505.5 | D8: =AVERAGEIF(Actuals!C6:C18,$D$5,Actuals!G6:G18) -> 0.074281574 | F8: =SUMIF(Actuals!C6:C18,$D$5,Actuals!D6:D18) -> 10022

Sheet Actuals
B2: Nykaa (FSN E-Commerce) — Quarterly Actuals
B3: Source: screener.in — Nykaa consolidated quarterly results (₹ Crore)
B5: Quarter | C5: Fiscal Year | D5: Revenue (₹ Cr) | E5: Expenses (₹ Cr) | F5: EBITDA (₹ Cr) | G5: EBITDA Margin %
B6: Jun 2023 | C6: FY24 | D6: 1422 | E6: 1348 | F6: =D6-E6 -> 74 | G6: =F6/D6 -> 0.052039381
B7: Sep 2023 | C7: FY24 | D7: 1507 | E7: 1426 | F7: =D7-E7 -> 81 | G7: =F7/D7 -> 0.053749171
B8: Dec 2023 | C8: FY24 | D8: 1789 | E8: 1690 | F8: =D8-E8 -> 99 | G8: =F8/D8 -> 0.055338178
B9: Mar 2024 | C9: FY24 | D9: 1668 | E9: 1575 | F9: =D9-E9 -> 93 | G9: =F9/D9 -> 0.055755396
B10: Jun 2024 | C10: FY25 | D10: 1746 | E10: 1650 | F10: =D10-E10 -> 96 | G10: =F10/D10 -> 0.054982818
B11: Sep 2024 | C11: FY25 | D11: 1875 | E11: 1771 | F11: =D11-E11 -> 104 | G11: =F11/D11 -> 0.055466667
B12: Dec 2024 | C12: FY25 | D12: 2267 | E12: 2126 | F12: =D12-E12 -> 141 | G12: =F12/D12 -> 0.062196736
B13: Mar 2025 | C13: FY25 | D13: 2062 | E13: 1928 | F13: =D13-E13 -> 134 | G13: =F13/D13 -> 0.064985451
B14: Jun 2025 | C14: FY26 | D14: 2155 | E14: 2014 | F14: =D14-E14 -> 141 | G14: =F14/D14 -> 0.065429234
B15: Sep 2025 | C15: FY26 | D15: 2346 | E15: 2187 | F15: =D15-E15 -> 159 | G15: =F15/D15 -> 0.067774936
B16: Dec 2025 | C16: FY26 | D16: 2873 | E16: 2644 | F16: =D16-E16 -> 229 | G16: =F16/D16 -> 0.079707623
B17: Mar 2026 | C17: FY26 | D17: 2648 | E17: 2425 | F17: =D17-E17 -> 223 | G17: =F17/D17 -> 0.084214502
B18: Jun 2026 | C18: FY27 | D18: 2782 | E18: 2546 | F18: =D18-E18 -> 236 | G18: =F18/D18 -> 0.084831057

Sheet Budget vs Actual
B2: Budget vs. Actual — FY26 Quarterly Variance
B3: Budget assumption: Revenue budgeted 5% below actual; Expenses budgeted at 93% cost-to-revenue ratio (see report for methodology)
B5: Revenue
B6: Quarter | C6: Budgeted Revenue | D6: Actual Revenue | E6: Variance (₹) | F6: Variance (%)
B7: Q1 FY26 | C7: =Actuals!D15*0.95 -> 2228.7 | D7: =Actuals!D15 -> 2346 | E7: =D7-C7 -> 117.3 | F7: =E7/C7 -> 0.052631579
B8: Q2 FY26 | C8: =Actuals!D16*0.95 -> 2729.35 | D8: =Actuals!D16 -> 2873 | E8: =D8-C8 -> 143.65 | F8: =E8/C8 -> 0.052631579
B9: Q3 FY26 | C9: =Actuals!D17*0.95 -> 2515.6 | D9: =Actuals!D17 -> 2648 | E9: =D9-C9 -> 132.4 | F9: =E9/C9 -> 0.052631579
B10: Q4 FY26 | C10: =Actuals!D18*0.95 -> 2642.9 | D10: =Actuals!D18 -> 2782 | E10: =D10-C10 -> 139.1 | F10: =E10/C10 -> 0.052631579
B13: Expenses
B14: Quarter | C14: Budgeted Expenses | D14: Actual Expenses | E14: Variance (₹) | F14: Variance (%) | G14: Actual Expense Ratio
B15: Q1 FY26 | C15: =C7*0.93 -> 2072.691 | D15: =Actuals!E15 -> 2187 | E15: =D15-C15 -> 114.309 | F15: =E15/C15 -> 0.055150044 | G15: =D15/Actuals!D15 -> 0.93222506
B16: Q2 FY26 | C16: =C8*0.93 -> 2538.2955 | D16: =Actuals!E16 -> 2644 | E16: =D16-C16 -> 105.7045 | F16: =E16/C16 -> 0.041643891 | G16: =D16/Actuals!D16 -> 0.92029238
B17: Q3 FY26 | C17: =C9*0.93 -> 2339.508 | D17: =Actuals!E17 -> 2425 | E17: =D17-C17 -> 85.492 | F17: =E17/C17 -> 0.036542726 | G17: =D17/Actuals!D17 -> 0.9157855
B18: Q4 FY26 | C18: =C10*0.93 -> 2457.897 | D18: =Actuals!E18 -> 2546 | E18: =D18-C18 -> 88.103 | F18: =E18/C18 -> 0.035844871 | G18: =D18/Actuals!D18 -> 0.91516894

Sheet Segments
B2: Revenue Mix by Segment
B3: Approximate FY25 mix, based on Nykaa investor presentations (Beauty & Personal Care vs Fashion)
B5: Segment | C5: Revenue Share (%)
B6: Beauty & Personal Care (BPC) | C6: 0.85
B7: Fashion | C7: 0.14
B8: Others | C8: 0.01
